xyzservices/__init__.py
xyzservices/_version.py
xyzservices/lib.py
xyzservices/providers.py
xyzservices/data/__init__.py
xyzservices/data/providers.json
xyzservices/tests/__init__.py
xyzservices/tests/test_lib.py
xyzservices/tests/test_providers.py
xyzservices-2022.4.0.data/data/share/xyzservices/providers.json
xyzservices-2022.4.0.dist-info/LICENSE
xyzservices-2022.4.0.dist-info/METADATA
xyzservices-2022.4.0.dist-info/WHEEL
xyzservices-2022.4.0.dist-info/top_level.txt
xyzservices-2022.4.0.dist-info/RECORD
