Metadata-Version: 2.1
Name: xyzservices
Version: 2022.4.0
Summary: Source of XYZ tiles providers
Home-page: https://github.com/geopandas/xyzservices
Author: Dani Arribas-Bel, Martin Fleischmann
Author-email: daniel.arribas.bel@gmail.com, martin@martinfleischmann.net
License: 3-Clause BSD
Platform: UNKNOWN
Classifier: License :: OSI Approved :: BSD License
Classifier: Programming Language :: Python :: 3
Classifier: Programming Language :: Python :: 3.7
Classifier: Programming Language :: Python :: 3 :: Only
Requires-Python: >=3.7
License-File: LICENSE
